papiry/__init__.py
papiry/download.py
papiry-0.1.0.dist-info/LICENSE
papiry-0.1.0.dist-info/METADATA
papiry-0.1.0.dist-info/WHEEL
papiry-0.1.0.dist-info/entry_points.txt
papiry-0.1.0.dist-info/RECORD
