Metadata-Version: 2.3
Name: papiry
Version: 0.1.0
Summary: Tool for organizing and downloading research papers.
License: MIT
Author: Matěj Kripner
Author-email: kripner@ufal.mff.cuni.cz
Requires-Python: >=3.11,<4.0
Classifier: License :: OSI Approved :: MIT License
Classifier: Programming Language :: Python :: 3
Classifier: Programming Language :: Python :: 3.11
Classifier: Programming Language :: Python :: 3.12
Classifier: Programming Language :: Python :: 3.13
Requires-Dist: pypdf (>=5.0.0,<6.0.0)
Requires-Dist: requests (>=2.31.0,<3.0.0)
